setup.py
plexshell/__init__.py
plexshell/model.py
plexshell/utils.py
plexshell.egg-info/PKG-INFO
plexshell.egg-info/SOURCES.txt
plexshell.egg-info/dependency_links.txt
plexshell.egg-info/entry_points.txt
plexshell.egg-info/requires.txt
plexshell.egg-info/top_level.txt
plexshell.egg-info/zip-safe
plexshell/commands/__init__.py
plexshell/commands/base.py
plexshell/commands/directory.py
plexshell/commands/plugin.py
plexshell/commands/settings.py
plexshell/commands/update.py
plexshell/scripts/__init__.py
plexshell/scripts/shell.py