Metadata-Version: 1.0
Name: plexshell
Version: 0.0.2
Summary: A shell to interact with the Plex Media Server
Home-page: https://github.com/jkp/plexshell
Author: Jamie Kirkpatrick
Author-email: jamie@plexinc.com
License: UNKNOWN
Download-URL: https://github.com/jkp/plexshell/downloads
Platform: UNKNOWN
